generatorGUI/GeneratorControl_UI.py
generatorGUI/Logo_rc.py
generatorGUI/__init__.py
generatorGUI/main.py
generatorGUI-0.1.0.dist-info/LICENSE
generatorGUI-0.1.0.dist-info/METADATA
generatorGUI-0.1.0.dist-info/WHEEL
generatorGUI-0.1.0.dist-info/top_level.txt
generatorGUI-0.1.0.dist-info/RECORD
