Metadata-Version: 2.1
Name: generatorGUI
Version: 0.1.0
Summary: Edit parameters for the Astra generator program and run generator using a GUI.
Home-page: https://pypi.python.org/pypi/generatorGUI
Author: Ao Liu
Author-email: ao@aoliu.tech
License: MIT
Keywords: generator,astra,GUI,PyQt5
Platform: UNKNOWN
Classifier: Development Status :: 1 - Planning
Classifier: Operating System :: OS Independent
Classifier: Topic :: Utilities
Classifier: License :: OSI Approved :: MIT License
Classifier: Programming Language :: Python :: 3
Requires-Python: >=3.0
